llm_cache.py
llm_cache_plugin-0.1.dist-info/licenses/LICENSE
llm_cache_plugin-0.1.dist-info/METADATA
llm_cache_plugin-0.1.dist-info/WHEEL
llm_cache_plugin-0.1.dist-info/entry_points.txt
llm_cache_plugin-0.1.dist-info/top_level.txt
llm_cache_plugin-0.1.dist-info/RECORD
