Metadata-Version: 2.4
Name: llm-cache-plugin
Version: 0.1
Summary: Check whether you've already run this prompt before calling the LLM
Author: Kevin Schaul
License-Expression: Apache-2.0
Project-URL: Homepage, https://github.com/kevinschaul/llm-cache-plugin
Project-URL: Changelog, https://github.com/kevinschaul/llm-cache-plugin/releases
Project-URL: Issues, https://github.com/kevinschaul/llm-cache-plugin/issues
Project-URL: CI, https://github.com/kevinschaul/llm-cache-plugin/actions
Requires-Python: >=3.9
License-File: LICENSE
Requires-Dist: llm
Provides-Extra: test
Requires-Dist: pytest; extra == "test"
Dynamic: license-file
